ambition_sites/__init__.py
ambition_sites/apps.py
ambition_sites/sites.py
ambition_sites/tests.py
ambition_sites/urls.py
ambition_sites/wsgi.py
ambition_sites-0.1.14.dist-info/AUTHORS
ambition_sites-0.1.14.dist-info/LICENSE
ambition_sites-0.1.14.dist-info/METADATA
ambition_sites-0.1.14.dist-info/WHEEL
ambition_sites-0.1.14.dist-info/top_level.txt
ambition_sites-0.1.14.dist-info/RECORD
